caty/__init__.py
caty/_dump_gen.py
caty/cli.py
caty/dump.py
caty/main.py
caty/plugins/__init__.py
caty/plugins/base.py
caty/plugins/bin.py
caty/plugins/cfg.py
caty/plugins/csv.py
caty/plugins/html.py
caty/plugins/ini.py
caty/plugins/json.py
caty/plugins/pickle.py
caty/plugins/sqlite.py
caty/plugins/toml.py
caty/plugins/txt.py
caty/plugins/yaml.py
caty-0.2423.2.dist-info/METADATA
caty-0.2423.2.dist-info/WHEEL
caty-0.2423.2.dist-info/entry_points.txt
caty-0.2423.2.dist-info/top_level.txt
caty-0.2423.2.dist-info/RECORD
